ftprci/__init__.py
ftprci/actuators.py
ftprci/controller.py
ftprci/estimator.py
ftprci/interface.py
ftprci/logger.py
ftprci/low_level.py
ftprci/main.py
ftprci/sensor.py
ftprci-0.2.30.dist-info/METADATA
ftprci-0.2.30.dist-info/WHEEL
ftprci-0.2.30.dist-info/top_level.txt
ftprci-0.2.30.dist-info/RECORD
