Metadata-Version: 2.2
Name: ftprci
Version: 0.2.30
Summary: Cross platform fast time python robot interface controller
Author-email: Ekter <ektermoi1@proton.me>
Project-URL: Homepage, https://github.com/Ekter/ftprci
Project-URL: Issues, https://github.com/Ekter/ftprci/issues
Classifier: Programming Language :: Python :: 3
Classifier: Programming Language :: Python :: Implementation :: MicroPython
Classifier: Programming Language :: Python :: Implementation :: CPython
Classifier: License :: OSI Approved :: GNU General Public License v3 (GPLv3)
Classifier: Operating System :: OS Independent
Requires-Python: >=3.7
Requires-Dist: numpy
Requires-Dist: smbus
Requires-Dist: pretlog
